<?xml version="1.0" encoding="utf-8"?>
<search>
  
  
  
  <entry>
    <title>无线安全审计工具-抓WiFi握手包教程</title>
    <link href="/post/35f17806.html"/>
    <url>/post/35f17806.html</url>
    
    <content type="html"><![CDATA[<p><strong>抓包工具可以复制下面口令打开咸鱼自行购买</strong></p><figure class="highlight 1c"><table><tr><td class="gutter"><pre><span class="line">1</span><br></pre></td><td class="code"><pre><code class="hljs 1c">【闲鱼】https:<span class="hljs-comment">//m.tb.cn/h.5zfcKhB?tk=sknNWKPGWpT</span><br></code></pre></td></tr></table></figure><p>这个抓包工具无需安装软件，手机就可以控制抓包，中文界面无需命令代码。</p><p>以下是图文教程，要是觉得字数太多懒得看，也可以<a href="https://www.bilibili.com/video/BV1nt421L76n/"><strong>点击这里看视频教程</strong></a></p><h2 id="1、设备供电并连接设备"><a href="#1、设备供电并连接设备" class="headerlink" title="1、设备供电并连接设备"></a>1、设备供电并连接设备</h2><p>将设备type-c口接入手机充电器或充电宝，设备上电后将会发出名称为ManagementAP的热点， 这个热点就是使用者用来连接和控制设备的，密码12345678</p><p><img src="/../imgs/$%7Bfiilename%7D/rd.png"></p><h2 id="2、连接热点选定目标设置抓包"><a href="#2、连接热点选定目标设置抓包" class="headerlink" title="2、连接热点选定目标设置抓包"></a>2、连接热点选定目标设置抓包</h2><p>连接热点后，打开浏览器（最好使用chrome浏览器）输入 <a href="http://192.168.4.1/">http://192.168.4.1</a> 回车访问，按下列方式设置抓包，注意先配置审计方式，再选择目标AP。目标AP要有人在使用的时候才会发送握手包，没有人用的AP无法抓包，信号强度最好不要低于-65。-46要比-50表示的信号强度要强。时间可以设置在30秒。这里注意按照下图所标的顺序进行设置。</p><p><img src="/../imgs/$%7Bfiilename%7D/3-1712396465466-5.png"></p><h2 id="3、等待设备自动抓包"><a href="#3、等待设备自动抓包" class="headerlink" title="3、等待设备自动抓包"></a>3、等待设备自动抓包</h2><p>等待设备运行（设备攻击时会自动把网卡调为混杂模式，你可能会断开与设备的连接，这是正常的，倒计时结束后刷新页面即可，无法刷新页面的可能是连接断开了，再手动连接到控制热点即可）。</p><p><img src="/../imgs/$%7Bfiilename%7D/daojishi.png"></p><h2 id="4、下载捕获到的握手包"><a href="#4、下载捕获到的握手包" class="headerlink" title="4、下载捕获到的握手包"></a>4、下载捕获到的握手包</h2><p>下载捕获到的握手包数据（格式为hccapx，这个格式是精简后的格式，包含破解所需的所有数据）。如果没有出现下面的界面就是这次没有抓到握手包，点重新测试再多试几次就可以。超过3次都抓不到很可能是目标AP当前没有人在使用，握手包要在有人用的时候才会产生，可以过个时间段再抓。也可以把时间调长点再试试，一般不建议超过100秒。</p><p><img src="/../imgs/$%7Bfiilename%7D/6.png"></p><h2 id="抓包成功后最后就是跑字典了，下一篇介绍：点击查看跑包演示"><a href="#抓包成功后最后就是跑字典了，下一篇介绍：点击查看跑包演示" class="headerlink" title="抓包成功后最后就是跑字典了，下一篇介绍：点击查看跑包演示"></a>抓包成功后最后就是<a href="https://pwifi.github.io/post/c7d23dcd.html">跑字典</a>了，下一篇介绍：<a href="https://pwifi.github.io/post/c7d23dcd.html">点击查看跑包演示</a></h2>]]></content>
    
    
    
  </entry>
  
  
  
  <entry>
    <title>软件演示软件字典下载</title>
    <link href="/post/c7d23dcd.html"/>
    <url>/post/c7d23dcd.html</url>
    
    <content type="html"><![CDATA[<h2 id="跑包视频演示：点击查看视频演示"><a href="#跑包视频演示：点击查看视频演示" class="headerlink" title="跑包视频演示：点击查看视频演示"></a>跑包视频演示：<a href="https://www.bilibili.com/video/BV11i421o7ES">点击查看视频演示</a></h2><h2 id="软下载地址"><a href="#软下载地址" class="headerlink" title="软下载地址"></a>软下载地址</h2><figure class="highlight awk"><table><tr><td class="gutter"><pre><span class="line">1</span><br><span class="line">2</span><br><span class="line">3</span><br></pre></td><td class="code"><pre><code class="hljs awk">链接: https:<span class="hljs-regexp">//</span>caiyun.<span class="hljs-number">139</span>.com<span class="hljs-regexp">/m/i</span>?<span class="hljs-number">2</span>dNxLkcbkVVwu<br><span class="hljs-regexp">/*69sQy26bq6UU:/</span> <br>复制本段信息，打开「中国移动云盘APP」获取。人人不限速。<br></code></pre></td></tr></table></figure><figure class="highlight awk"><table><tr><td class="gutter"><pre><span class="line">1</span><br></pre></td><td class="code"><pre><code class="hljs awk">备用下载：https:<span class="hljs-regexp">//</span>pan.quark.cn<span class="hljs-regexp">/s/</span>f04a29a8f342<br></code></pre></td></tr></table></figure><h2 id="密码字典下载地址"><a href="#密码字典下载地址" class="headerlink" title="密码字典下载地址"></a>密码字典下载地址</h2><p>新华字典最后更新+（推荐）</p><figure class="highlight awk"><table><tr><td class="gutter"><pre><span class="line">1</span><br><span class="line">2</span><br><span class="line">3</span><br></pre></td><td class="code"><pre><code class="hljs awk">链接: https:<span class="hljs-regexp">//</span>caiyun.<span class="hljs-number">139</span>.com<span class="hljs-regexp">/m/i</span>?<span class="hljs-number">2</span>dL3xoiNDw7nk<br><span class="hljs-regexp">/*c9s2wye3QngK:/</span> <br>复制本段信息，打开「中国移动云盘APP」获取。人人不限速<br></code></pre></td></tr></table></figure><p>弱口令（低配电脑用）</p><figure class="highlight awk"><table><tr><td class="gutter"><pre><span class="line">1</span><br></pre></td><td class="code"><pre><code class="hljs awk">https:<span class="hljs-regexp">//</span>pan.quark.cn<span class="hljs-regexp">/s/</span><span class="hljs-number">56145</span>d3d8094<br></code></pre></td></tr></table></figure>]]></content>
    
    
    
  </entry>
  
  
  
  
</search>
